LoginOrRegister/__init__.py
LoginOrRegister/auth.py
LoginOrRegister/digit_init.py
digit_client/__init__.py
digit_client/api_client.py
digit_client/config.py
digit_client/exceptions.py
digit_client/request_config.py
digit_client/utils.py
digit_client/models/ActionRequest.py
digit_client/models/AuthorizationRequest.py
digit_client/models/Encrypts.py
digit_client/models/Indexer.py
digit_client/models/Otp.py
digit_client/models/Report.py
digit_client/models/ServiceRequest.py
digit_client/models/ShortenRequest.py
digit_client/models/Transactions.py
digit_client/models/__init__.py
digit_client/models/auth.py
digit_client/models/boundary.py
digit_client/models/businessServicesV2.py
digit_client/models/citizen_user.py
digit_client/models/filestore.py
digit_client/models/idrequest.py
digit_client/models/localization.py
digit_client/models/mdms.py
digit_client/models/mdms_v2.py
digit_client/models/search_models.py
digit_client/models/user.py
digit_client/models/workflow.py
digit_client/services/Encrypts.py
digit_client/services/Indexer.py
digit_client/services/Report.py
digit_client/services/ServiceRequest.py
digit_client/services/ShortenRequest.py
digit_client/services/Transaction.py
digit_client/services/__init__.py
digit_client/services/authenticate.py
digit_client/services/authorize.py
digit_client/services/boundary.py
digit_client/services/filestore.py
digit_client/services/idrequest.py
digit_client/services/localization.py
digit_client/services/master_data_v1.py
digit_client/services/mdms_v2.py
digit_client/services/otp.py
digit_client/services/pdf.py
digit_client/services/user_service.py
digit_client/services/workflow.py
digit_client-1.0.4.dist-info/METADATA
digit_client-1.0.4.dist-info/WHEEL
digit_client-1.0.4.dist-info/entry_points.txt
digit_client-1.0.4.dist-info/top_level.txt
digit_client-1.0.4.dist-info/RECORD
