Metadata-Version: 2.2
Name: Digit-Client
Version: 1.0.4
Home-page: https://github.com/Priyansuvaish/digit_lib.git
Author: eGov Foundation
Author-email: priyanshu.vaish@egovernments.org
Classifier: Development Status :: 3 - Alpha
Classifier: Intended Audience :: Developers
Classifier: License :: OSI Approved :: MIT License
Classifier: Programming Language :: Python :: 3.6
Classifier: Programming Language :: Python :: 3.7
Classifier: Programming Language :: Python :: 3.8
Classifier: Programming Language :: Python :: 3.9
Requires-Python: >=3.6
Requires-Dist: requests>=2.25.1
Requires-Dist: jsonschema>=4.0.0
Requires-Dist: werkzeug>=3.0.1
Requires-Dist: python-dotenv>=1.0.0
Dynamic: author
Dynamic: author-email
Dynamic: classifier
Dynamic: description
Dynamic: description-content-type
Dynamic: home-page
Dynamic: requires-dist
Dynamic: requires-python
